LICENSE
MANIFEST.in
README.rst
setup.cfg
setup.py
DRF_commands/__init__.py
DRF_commands/apps.py
DRF_commands.egg-info/PKG-INFO
DRF_commands.egg-info/SOURCES.txt
DRF_commands.egg-info/dependency_links.txt
DRF_commands.egg-info/requires.txt
DRF_commands.egg-info/top_level.txt
DRF_commands/management/__init__.py
DRF_commands/management/core.py
DRF_commands/management/commands/APIView.py
DRF_commands/management/commands/APIView.txt
DRF_commands/management/commands/CreateAPIView.py
DRF_commands/management/commands/CreateAPIView.txt
DRF_commands/management/commands/DestroyAPIView.py
DRF_commands/management/commands/DestroyAPIView.txt
DRF_commands/management/commands/ListAPIView.py
DRF_commands/management/commands/ListAPIView.txt
DRF_commands/management/commands/ListCreateAPIView.py
DRF_commands/management/commands/ListCreateAPIView.txt
DRF_commands/management/commands/RetrieveAPIView.py
DRF_commands/management/commands/RetrieveAPIView.txt
DRF_commands/management/commands/RetrieveDestroyAPIView.py
DRF_commands/management/commands/RetrieveDestroyAPIView.txt
DRF_commands/management/commands/RetrieveUpdateAPIView.py
DRF_commands/management/commands/RetrieveUpdateAPIView.txt
DRF_commands/management/commands/RetrieveUpdateDestroyAPIView.py
DRF_commands/management/commands/RetrieveUpdateDestroyAPIView.txt
DRF_commands/management/commands/UpdateAPIView.py
DRF_commands/management/commands/UpdateAPIView.txt
DRF_commands/management/commands/__init__.py
DRF_commands/management/commands/apps.py.txt
DRF_commands/management/commands/createApp.py
DRF_commands/management/commands/createSerializer.py
DRF_commands/management/commands/serializer.txt
DRF_commands/management/commands/urls.py.txt